{
	"shows": [
		{
			"stages": [
				{
					"name": "南霸天",
					"artists": [
						{
							"name": "INFERNAL CHAOS",
							"start": "2021-03-27T12:20",
							"end": "2021-03-27T13:00"
						},
						{
							"name": "康士坦的變化球",
							"start": "2021-03-27T13:40",
							"end": "2021-03-27T14:20"
						},
						{
							"name": "拍謝少年",
							"start": "2021-03-27T15:00",
							"end": "2021-03-27T15:40"
						},
						{
							"name": "羅時豐 ft.法蘭",
							"start": "2021-03-27T16:20",
							"end": "2021-03-27T17:00"
						},
						{
							"name": "血肉果汁機 ft.美麗本人",
							"start": "2021-03-27T17:40",
							"end": "2021-03-27T18:20"
						},
						{
							"name": "Leo王",
							"start": "2021-03-27T19:00",
							"end": "2021-03-27T19:40"
						},
						{
							"name": "閃靈 ft.唐鳳",
							"start": "2021-03-27T20:40",
							"end": "2021-03-27T21:20"
						}
					]
				},
				{
					"name": "海龍王",
					"artists": [
						{
							"name": "落差草原WWWW",
							"start": "2021-03-27T14:00",
							"end": "2021-03-27T14:40"
						},
						{
							"name": "持修",
							"start": "2021-03-27T15:20",
							"end": "2021-03-27T16:00"
						},
						{
							"name": "春豔",
							"start": "2021-03-27T16:40",
							"end": "2021-03-27T17:20"
						},
						{
							"name": "鼓鼓 呂思緯 ft.老王(Green! Eyes)",
							"start": "2021-03-27T18:00",
							"end": "2021-03-27T18:40"
						},
						{
							"name": "台灣雅典娜 與她的 黃金聖鬥士 (Empty ORio + punkhoo胖虎)",
							"start": "2021-03-27T19:40",
							"end": "2021-03-27T21:00"
						}
					]
				},
				{
					"name": "女神龍",
					"artists": [
						{
							"name": "厭世少年",
							"start": "2021-03-27T11:40",
							"end": "2021-03-27T12:20"
						},
						{
							"name": "隨性",
							"start": "2021-03-27T13:00",
							"end": "2021-03-27T13:40"
						},
						{
							"name": "董事長樂團 ft.Lulu 黃路梓茵",
							"start": "2021-03-27T14:20",
							"end": "2021-03-27T15:00"
						},
						{
							"name": "Beyond Cure ft.Ru味春捲",
							"start": "2021-03-27T15:40",
							"end": "2021-03-27T16:20"
						},
						{
							"name": "來吧!焙焙!",
							"start": "2021-03-27T17:00",
							"end": "2021-03-27T17:40"
						},
						{
							"name": "告五人",
							"start": "2021-03-27T18:20",
							"end": "2021-03-27T19:00"
						},
						{
							"name": "Tizzy Bac",
							"start": "2021-03-27T19:40",
							"end": "2021-03-27T20:20"
						}
					]
				},
				{
					"name": "卡魔麥",
					"artists": [
						{
							"name": "一點生",
							"start": "2021-03-27T12:10",
							"end": "2021-03-27T12:50"
						},
						{
							"name": "JADE",
							"start": "2021-03-27T13:30",
							"end": "2021-03-27T14:10"
						},
						{
							"name": "Easy Shen Gang ft.周穆",
							"start": "2021-03-27T14:50",
							"end": "2021-03-27T15:30"
						},
						{
							"name": "2HRs",
							"start": "2021-03-27T16:10",
							"end": "2021-03-27T16:50"
						},
						{
							"name": "LINION",
							"start": "2021-03-27T17:30",
							"end": "2021-03-27T18:10"
						},
						{
							"name": "昆蟲白",
							"start": "2021-03-27T18:50",
							"end": "2021-03-27T19:30"
						},
						{
							"name": "Green!Eyes",
							"start": "2021-03-27T20:10",
							"end": "2021-03-27T20:50"
						}
					]
				},
				{
					"name": "出頭天",
					"artists": [
						{
							"name": "水源",
							"start": "2021-03-27T12:40",
							"end": "2021-03-27T13:20"
						},
						{
							"name": "緩緩",
							"start": "2021-03-27T14:00",
							"end": "2021-03-27T14:40"
						},
						{
							"name": "The Tic Tac",
							"start": "2021-03-27T15:20",
							"end": "2021-03-27T16:00"
						},
						{
							"name": "柯泯薰",
							"start": "2021-03-27T16:40",
							"end": "2021-03-27T17:20"
						}
					]
				},
				{
					"name": "海波浪",
					"artists": [
						{
							"name": "My Cat Eats My Hand",
							"start": "2021-03-27T11:40",
							"end": "2021-03-27T12:20"
						},
						{
							"name": "孩子王",
							"start": "2021-03-27T13:00",
							"end": "2021-03-27T13:40"
						},
						{
							"name": "萬隆",
							"start": "2021-03-27T14:20",
							"end": "2021-03-27T15:00"
						},
						{
							"name": "百合花",
							"start": "2021-03-27T15:40",
							"end": "2021-03-27T16:20"
						},
						{
							"name": "必順鄉村",
							"start": "2021-03-27T17:00",
							"end": "2021-03-27T17:40"
						},
						{
							"name": "熱寫生",
							"start": "2021-03-27T18:20",
							"end": "2021-03-27T19:00"
						},
						{
							"name": "當代電影大師",
							"start": "2021-03-27T19:40",
							"end": "2021-03-27T20:20"
						}
					]
				},
				{
					"name": "大雄丸",
					"artists": [
						{
							"name": "台北♡紐約 (Mia ft.9m88)",
							"start": "2021-03-27T13:00",
							"end": "2021-03-27T14:00"
						},
						{
							"name": "Marz23 ft.DJ GROUND",
							"start": "2021-03-27T15:00",
							"end": "2021-03-27T16:00"
						},
						{
							"name": "台北柯公子 (家洋 ft.震東)",
							"start": "2021-03-27T17:00",
							"end": "2021-03-27T18:00"
						}
					]
				},
				{
					"name": "藍寶石",
					"artists": [
						{
							"name": "毀容姐妹會",
							"start": "2021-03-27T13:40",
							"end": "2021-03-27T14:20"
						},
						{
							"name": "開樂亭凡笑",
							"start": "2021-03-27T15:00",
							"end": "2021-03-27T15:40"
						},
						{
							"name": "黃豪平 x 凱莉(百靈果)",
							"start": "2021-03-27T16:20",
							"end": "2021-03-27T17:00"
						}
					]
				},
				{
					"name": "青春夢",
					"artists": [
						{
							"name": "楊士弘",
							"start": "2021-03-27T13:00",
							"end": "2021-03-27T13:40"
						},
						{
							"name": "MIND THE GAP",
							"start": "2021-03-27T14:20",
							"end": "2021-03-27T15:00"
						},
						{
							"name": "煙雨飄渺",
							"start": "2021-03-27T15:40",
							"end": "2021-03-27T16:20"
						},
						{
							"name": "青虫aoi",
							"start": "2021-03-27T17:00",
							"end": "2021-03-27T17:40"
						}
					]
				},
				{
					"name": "小港祭",
					"artists": [
						{
							"name": "T.F.L",
							"start": "2021-03-27T15:20",
							"end": "2021-03-27T16:20"
						},
						{
							"name": "勝野武士",
							"start": "2021-03-27T16:20",
							"end": "2021-03-27T17:10"
						},
						{
							"name": "沈髒三",
							"start": "2021-03-27T17:10",
							"end": "2021-03-27T17:50"
						},
						{
							"name": "Mr. Kloud ft. FunkyMo",
							"start": "2021-03-27T17:50",
							"end": "2021-03-27T19:20"
						}
					]
				}
			]
		},
		{
			"stages": [
				{
					"name": "南霸天",
					"artists": [
						{
							"name": "東京中央線",
							"start": "2021-03-28T12:20",
							"end": "2021-03-28T13:00"
						},
						{
							"name": "非人物種",
							"start": "2021-03-28T13:40",
							"end": "2021-03-28T14:20"
						},
						{
							"name": "傷心欲絕",
							"start": "2021-03-28T15:00",
							"end": "2021-03-28T15:40"
						},
						{
							"name": "美秀集團",
							"start": "2021-03-28T16:20",
							"end": "2021-03-28T17:00"
						},
						{
							"name": "麋先生 ft.Vivian 徐若瑄",
							"start": "2021-03-28T17:50",
							"end": "2021-03-28T18:50"
						},
						{
							"name": "滅火器",
							"start": "2021-03-28T19:50",
							"end": "2021-03-28T20:30"
						},
						{
							"name": "茄子蛋",
							"start": "2021-03-28T21:10",
							"end": "2021-03-28T21:50"
						}
					]
				},
				{
					"name": "海龍王",
					"artists": [
						{
							"name": "OBSESS",
							"start": "2021-03-28T12:40",
							"end": "2021-03-28T13:20"
						},
						{
							"name": "五五身",
							"start": "2021-03-28T14:00",
							"end": "2021-03-28T14:40"
						},
						{
							"name": "風籟坊",
							"start": "2021-03-28T15:20",
							"end": "2021-03-28T16:00"
						},
						{
							"name": "聲子蟲",
							"start": "2021-03-28T16:40",
							"end": "2021-03-28T17:20"
						},
						{
							"name": "The Fur",
							"start": "2021-03-28T18:00",
							"end": "2021-03-28T18:40"
						},
						{
							"name": "FUTURE AFTER",
							"start": "2021-03-28T19:20",
							"end": "2021-03-28T20:00"
						},
						{
							"name": "陳珊妮 ft.呂士軒",
							"start": "2021-03-28T20:40",
							"end": "2021-03-28T21:20"
						}
					]
				},
				{
					"name": "女神龍",
					"artists": [
						{
							"name": "海豚刑警",
							"start": "2021-03-28T11:40",
							"end": "2021-03-28T12:20"
						},
						{
							"name": "阿飛西雅",
							"start": "2021-03-28T13:00",
							"end": "2021-03-28T13:40"
						},
						{
							"name": "AKB48 Team TP ft.黃西田",
							"start": "2021-03-28T14:20",
							"end": "2021-03-28T15:00"
						},
						{
							"name": "大象體操 ft.高雄市管樂團",
							"start": "2021-03-28T15:50",
							"end": "2021-03-28T16:30"
						},
						{
							"name": "鄭宜農",
							"start": "2021-03-28T17:20",
							"end": "2021-03-28T18:00"
						},
						{
							"name": "YELLOW",
							"start": "2021-03-28T18:50",
							"end": "2021-03-28T19:30"
						},
						{
							"name": "9m88 ft.奕碩",
							"start": "2021-03-28T20:30",
							"end": "2021-03-28T21:10"
						}
					]
				},
				{
					"name": "卡魔麥",
					"artists": [
						{
							"name": "謎路人",
							"start": "2021-03-28T13:30",
							"end": "2021-03-28T14:10"
						},
						{
							"name": "逃走鮑伯",
							"start": "2021-03-28T14:50",
							"end": "2021-03-28T15:30"
						},
						{
							"name": "林以樂",
							"start": "2021-03-28T16:10",
							"end": "2021-03-28T16:50"
						},
						{
							"name": "Cresent Lament 恆月三途",
							"start": "2021-03-28T17:30",
							"end": "2021-03-28T18:10"
						},
						{
							"name": "吳柏蒼",
							"start": "2021-03-28T18:50",
							"end": "2021-03-28T19:30"
						},
						{
							"name": "莫宰羊",
							"start": "2021-03-28T20:10",
							"end": "2021-03-28T20:50"
						}
					]
				},
				{
					"name": "出頭天",
					"artists": [
						{
							"name": "Yaway-Mawring 雅維.茉芮",
							"start": "2021-03-28T12:40",
							"end": "2021-03-28T13:20"
						},
						{
							"name": "南西肯恩",
							"start": "2021-03-28T14:00",
							"end": "2021-03-28T14:40"
						},
						{
							"name": "米莎與戇仔",
							"start": "2021-03-28T15:20",
							"end": "2021-03-28T16:00"
						},
						{
							"name": "黃子軒與山平快",
							"start": "2021-03-28T16:40",
							"end": "2021-03-28T17:20"
						}
					]
				},
				{
					"name": "海波浪",
					"artists": [
						{
							"name": "Rain and Picture",
							"start": "2021-03-28T11:40",
							"end": "2021-03-28T12:20"
						},
						{
							"name": "麥琪麥琪",
							"start": "2021-03-28T13:00",
							"end": "2021-03-28T13:40"
						},
						{
							"name": "魚條",
							"start": "2021-03-28T14:20",
							"end": "2021-03-28T15:00"
						},
						{
							"name": "Lazy Habits",
							"start": "2021-03-28T15:40",
							"end": "2021-03-28T16:20"
						},
						{
							"name": "彼岸曙光",
							"start": "2021-03-28T17:00",
							"end": "2021-03-28T17:40"
						},
						{
							"name": "眠腦",
							"start": "2021-03-28T18:20",
							"end": "2021-03-28T19:00"
						},
						{
							"name": "倒車入庫",
							"start": "2021-03-28T19:40",
							"end": "2021-03-28T20:20"
						}
					]
				},
				{
					"name": "大雄丸",
					"artists": [
						{
							"name": "台灣通勤第一品牌",
							"start": "2021-03-28T13:00",
							"end": "2021-03-28T14:00"
						},
						{
							"name": "YALLOW 黃宣 ft. Ku da Yeast",
							"start": "2021-03-28T15:00",
							"end": "2021-03-28T16:00"
						},
						{
							"name": "國國 ft. 喬瑟夫ChillSeph",
							"start": "2021-03-28T17:00",
							"end": "2021-03-28T18:00"
						}
					]
				},
				{
					"name": "藍寶石",
					"artists": [
						{
							"name": "Ponay的原式Cover",
							"start": "2021-03-28T13:40",
							"end": "2021-03-28T14:20"
						},
						{
							"name": "東區德 x RayRay",
							"start": "2021-03-28T15:00",
							"end": "2021-03-28T15:40"
						},
						{
							"name": "黑狼 遠看像朵花 那卡西",
							"start": "2021-03-28T16:20",
							"end": "2021-03-28T17:00"
						}
					]
				},
				{
					"name": "青春夢",
					"artists": [
						{
							"name": "吾橋有水",
							"start": "2021-03-28T13:00",
							"end": "2021-03-28T13:40"
						},
						{
							"name": "白鐵仔",
							"start": "2021-03-28T14:20",
							"end": "2021-03-28T15:00"
						},
						{
							"name": "Dudu King & 萬能麥斯",
							"start": "2021-03-28T15:40",
							"end": "2021-03-28T16:20"
						},
						{
							"name": "TOBE",
							"start": "2021-03-28T17:00",
							"end": "2021-03-28T17:40"
						}
					]
				},
				{
					"name": "小港祭",
					"artists": [
						{
							"name": "Da Wang",
							"start": "2021-03-28T15:00",
							"end": "2021-03-28T15:50"
						},
						{
							"name": "億思 lan Lin ft. 詹士賢",
							"start": "2021-03-28T15:50",
							"end": "2021-03-28T17:00"
						},
						{
							"name": "Litro",
							"start": "2021-03-28T17:00",
							"end": "2021-03-28T17:50"
						},
						{
							"name": "賴皮 Mr. Skin ft. 浩庭",
							"start": "2021-03-28T17:50",
							"end": "2021-03-28T19:00"
						}
					]
				}
			]
		}
	]
}
